my_sample_package/__init__.py
my_sample_package/my_module.py
my_sample_package-0.1.dist-info/LICENSE
my_sample_package-0.1.dist-info/METADATA
my_sample_package-0.1.dist-info/WHEEL
my_sample_package-0.1.dist-info/top_level.txt
my_sample_package-0.1.dist-info/RECORD
