Metadata-Version: 2.1
Name: my-sample-package
Version: 0.1
Summary: A simple package to add two numbers
Author: periyanayagam
Author-email: periyanayagam.anthonysamy@itbeezone.in
Classifier: Programming Language :: Python :: 3
Classifier: License :: OSI Approved :: MIT License
Classifier: Operating System :: OS Independent
Requires-Python: >=3.6
License-File: LICENSE
